LICENSE
spectrally_constrained_LVMs/__init__.py
spectrally_constrained_LVMs/cost_functions.py
spectrally_constrained_LVMs/helper_methods.py
spectrally_constrained_LVMs/negen_approx.py
spectrally_constrained_LVMs/spectral_constraint.py
spectrally_constrained_LVMs/spectrally_constrained_model.py
spectrally_constrained_lvms-0.1.3.dist-info/LICENSE
spectrally_constrained_lvms-0.1.3.dist-info/METADATA
spectrally_constrained_lvms-0.1.3.dist-info/WHEEL
spectrally_constrained_lvms-0.1.3.dist-info/RECORD
