Metadata-Version: 2.1
Name: spectrally-constrained-lvms
Version: 0.1.3
Summary: An optimisation implementation of linear transforms with a spectral constraint.
Home-page: https://github.com/RyanBalshaw/spectrally-constrained-LVMs
License: MIT
Keywords: Linear LVMs,spectral constraint,PCA,ICA
Author: Ryan Balshaw
Author-email: ryanbalshaw81@gmail.com
Maintainer: Ryan Balshaw
Maintainer-email: ryanbalshaw81@gmail.com
Requires-Python: >=3.10,<4.0
Classifier: Development Status :: 4 - Beta
Classifier: License :: OSI Approved :: MIT License
Classifier: Programming Language :: Python :: 3
Classifier: Programming Language :: Python :: 3.10
Classifier: Programming Language :: Python :: 3.11
Classifier: Programming Language :: Python :: 3
Classifier: Programming Language :: Python :: Implementation
Classifier: Topic :: Scientific/Engineering
Requires-Dist: matplotlib (>=3.5.2,<4.0.0)
Requires-Dist: numpy (>=1.23.1,<2.0.0)
Requires-Dist: scikit-learn (>=1.1.2,<2.0.0)
Requires-Dist: scipy (>=1.8.1,<2.0.0)
Requires-Dist: sympy (>=1.11.1,<2.0.0)
Requires-Dist: tqdm (>=4.64.1,<5.0.0)
Project-URL: Bug tracker, https://github.com/RyanBalshaw/spectrally-constrained-LVMs/issues
Project-URL: Documentation, https://github.com/RyanBalshaw/spectrally-constrained-LVMs
Project-URL: Repository, https://github.com/RyanBalshaw/spectrally-constrained-LVMs
